Workbook

Sheet Dashboard
B2: eBay Hunting Dashboard
B3: Updates automatically from the Hunting tab.
B5: Products tracked | D5: ✅ GO | F5: ⚠ CHECK | H5: ❌ SKIP
B6: =COUNTA(Hunting!B5:B204) -> 3 | D6: =COUNTIF(Hunting!AJ5:AJ204,"✅ GO") -> 1 | F6: =COUNTIF(Hunting!AJ5:AJ204,"⚠ CHECK") -> 1 | H6: =COUNTIF(Hunting!AJ5:AJ204,"❌ SKIP") -> 1
B9: Avg profit (GO) $ | D9: Avg ROI (all) | F9: Best profit $ | H9: Retail-source warnings
B10: =IFERROR(AVERAGEIF(Hunting!AJ5:AJ204,"✅ GO",Hunting!AC5:AC204),0) -> 7.2792824 | D10: =IFERROR(AVERAGE(Hunting!AF5:AF204),0) -> 0.5602319 | F10: =IFERROR(MAX(Hunting!AC5:AC204),0) -> 7.2792824 | H10: =COUNTIF(Hunting!AI5:AI204,"⚠*") -> 1
B14: Top 5 products by net profit
B15: Rank | C15: Product | H15: Net Profit $ | I15: ROI % | J15: Status
B16: 1 | C16: =IFERROR(INDEX(Hunting!B5:B204,MATCH(LARGE(Hunting!AC5:AC204,1),Hunting!AC5:AC204,0)),"") -> Kitchen Sink Sponge Holder, Stainless | H16: =IFERROR(LARGE(Hunting!AC5:AC204,1),"") -> 7.2792824 | I16: =IFERROR(INDEX(Hunting!AF5:AF204,MATCH(LARGE(Hunting!AC5:AC204,1),Hunting!AC5:AC204,0)),"") -> 0.9099103 | J16: =IFERROR(INDEX(Hunting!AJ5:AJ204,MATCH(LARGE(Hunting!AC5:AC204,1),Hunting!AC5:AC204,0)),"") -> ✅ GO
B17: 2 | C17: =IFERROR(INDEX(Hunting!B5:B204,MATCH(LARGE(Hunting!AC5:AC204,2),Hunting!AC5:AC204,0)),"") -> Stainless Steel Lemon Squeezer | H17: =IFERROR(LARGE(Hunting!AC5:AC204,2),"") -> 6.9946849 | I17: =IFERROR(INDEX(Hunting!AF5:AF204,MATCH(LARGE(Hunting!AC5:AC204,2),Hunting!AC5:AC204,0)),"") -> 0.68913152 | J17: =IFERROR(INDEX(Hunting!AJ5:AJ204,MATCH(LARGE(Hunting!AC5:AC204,2),Hunting!AC5:AC204,0)),"") -> ⚠ CHECK
B18: 3 | C18: =IFERROR(INDEX(Hunting!B5:B204,MATCH(LARGE(Hunting!AC5:AC204,3),Hunting!AC5:AC204,0)),"") -> Scott Paper Towels, Choose-A-Sheet | H18: =IFERROR(LARGE(Hunting!AC5:AC204,3),"") -> 0.55851263 | I18: =IFERROR(INDEX(Hunting!AF5:AF204,MATCH(LARGE(Hunting!AC5:AC204,3),Hunting!AC5:AC204,0)),"") -> 0.081653893 | J18: =IFERROR(INDEX(Hunting!AJ5:AJ204,MATCH(LARGE(Hunting!AC5:AC204,3),Hunting!AC5:AC204,0)),"") -> ❌ SKIP
B19: 4 | C19: =IFERROR(INDEX(Hunting!B5:B204,MATCH(LARGE(Hunting!AC5:AC204,4),Hunting!AC5:AC204,0)),"") | H19: =IFERROR(LARGE(Hunting!AC5:AC204,4),"") | I19: =IFERROR(INDEX(Hunting!AF5:AF204,MATCH(LARGE(Hunting!AC5:AC204,4),Hunting!AC5:AC204,0)),"") | J19: =IFERROR(INDEX(Hunting!AJ5:AJ204,MATCH(LARGE(Hunting!AC5:AC204,4),Hunting!AC5:AC204,0)),"")
B20: 5 | C20: =IFERROR(INDEX(Hunting!B5:B204,MATCH(LARGE(Hunting!AC5:AC204,5),Hunting!AC5:AC204,0)),"") | H20: =IFERROR(LARGE(Hunting!AC5:AC204,5),"") | I20: =IFERROR(INDEX(Hunting!AF5:AF204,MATCH(LARGE(Hunting!AC5:AC204,5),Hunting!AC5:AC204,0)),"") | J20: =IFERROR(INDEX(Hunting!AJ5:AJ204,MATCH(LARGE(Hunting!AC5:AC204,5),Hunting!AC5:AC204,0)),"")

Sheet Settings
A1: eBay Fee Settings (US, 2026)
A2: Yellow cells are inputs. Change them here and every product in the Hunting sheet updates.
A4: Setting | B4: Value | C4: Note / source
A5: Final value fee (most categories) | B5: 0.136 | C5: eBay US, no Store / Starter Store: 13.6% on first $7,500. Some categories differ (books 15.3%, jewellery 15%) — use the FVF override column. Source: frooition.com/ebay-fee-calculator, sellerfeecalc.com (Oct 2026).
A6: Per-order fee (order ≤ threshold) | B6: 0.3 | C6: eBay per-order fee for orders of $10 or less.
A7: Per-order fee (order > threshold) | B7: 0.4 | C7: eBay per-order fee for orders over $10.
A8: Per-order fee threshold | B8: 10 | C8: Order total (incl. tax) at which the per-order fee switches.
A9: International fee | B9: 0.0165 | C9: Charged on international sales. Sources report 1.65%; confirm on eBay Seller Hub.
A10: Average US sales tax | B10: 0.07 | C10: Assumption. eBay charges its % fees on the total incl. sales tax.
A11: Default ad rate (Promoted General) | B11: 0.03 | C11: Assumption. Used when a row leaves Ad Rate blank.
A12: Payout / withdrawal fee | B12: 0.01 | C12: Assumption for Payoneer/bank withdrawal. Set to your real rate.
A13: Returns & loss reserve | B13: 0.03 | C13: Assumption: money set aside per sale for returns, refunds, damage.
A14: USD → PKR rate | B14: 280 | C14: Assumption. Update to today's rate.
A15: Minimum profit per sale | B15: 3 | C15: Your rule: a product needs at least this profit to be GO.
A16: Minimum ROI | B16: 0.25 | C16: Your rule: profit ÷ cost must be at least this to be GO.
A17: Minimum sell-through | B17: 0.4 | C17: Your rule: sold ÷ (sold + active) — demand check. Leave sold/active blank to skip.

Sheet Hunting
A1: eBay Product Hunting Sheet — 2026
A2: Fill the YELLOW columns only. Grey columns calculate automatically from the Settings tab. Fees: US 2026 (13.6% FVF + $0.30/$0.40 per order, charged on total incl. sales tax).
A3: PRODUCT | G3: COST | K3: SELLING | P3: MARKET | S3: EBAY FEES | Z3: PROFIT | AG3: PRICING | AI3: DECISION
A4: # | B4: Product Name | C4: Source Site | D4: Source Link | E4: eBay Link (sold comp) | F4: Category | G4: Source Price $ | H4: Source Shipping $ | I4: Other Cost $ | J4: Total Cost $ | K4: eBay Sale Price $ | L4: Shipping Charged $ | M4: Ad Rate % (blank = default) | N4: FVF % override | O4: Intl Sale? (Y/N) | P4: Sold Last 30 Days | Q4: Active Competitors | R4: Sell-Through % | S4: Order Total $ | T4: Est. Sales Tax $ | U4: Final Value Fee $ | V4: Per-Order Fee $ | W4: Intl Fee $ | X4: Ad Fee $ | Y4: Total eBay Fees $ | Z4: eBay Payout $ | AA4: Withdrawal Fee $ | AB4: Returns Reserve $ | AC4: NET PROFIT $ | AD4: Net Profit PKR | AE4: Margin % | AF4: ROI % | AG4: Break-even Price $ | AH4: Price for Min Profit $ | AI4: Source Check | AJ4: STATUS | AK4: Note
A5: =IF(B5="","",ROW()-4) -> 1 | B5: Scott Paper Towels, Choose-A-Sheet | C5: Amazon | D5: https://www.amazon.com/ | E5: https://www.ebay.com/ | F5: Household | G5: 6.84 | H5: 0 | I5: 0 | J5: =IF(G5="","",G5+N(H5)+N(I5)) -> 6.84 | K5: 9.94 | L5: 0 | O5: N | P5: 12 | Q5: 40 | R5: =IF(OR(P5="",Q5=""),"",P5/(P5+Q5)) -> 0.23076923 | S5: =IF(OR(K5="",G5=""),"",K5+N(L5)) -> 9.94 | T5: =IF(OR(K5="",G5=""),"",S5*Settings!$B$10) -> 0.6958 | U5: =IF(OR(K5="",G5=""),"",(S5+T5)*IF(N5="",Settings!$B$5,N5)) -> 1.4464688 | V5: =IF(OR(K5="",G5=""),"",IF(S5+T5<=Settings!$B$8,Settings!$B$6,Settings!$B$7)) -> 0.4 | W5: =IF(OR(K5="",G5=""),"",S5*IF(UPPER(O5)="Y",Settings!$B$9,0)) -> 0 | X5: =IF(OR(K5="",G5=""),"",(S5+T5)*IF(M5="",Settings!$B$11,M5)) -> 0.319074 | Y5: =IF(OR(K5="",G5=""),"",U5+V5+W5+X5) -> 2.1655428 | Z5: =IF(OR(K5="",G5=""),"",S5-Y5) -> 7.7744572 | AA5: =IF(OR(K5="",G5=""),"",Z5*Settings!$B$12) -> 0.077744572 | AB5: =IF(OR(K5="",G5=""),"",S5*Settings!$B$13) -> 0.2982 | AC5: =IF(OR(K5="",G5=""),"",Z5-AA5-AB5-J5) -> 0.55851263 | AD5: =IF(OR(K5="",G5=""),"",AC5*Settings!$B$14) -> 156.38354 | AE5: =IF(OR(K5="",G5=""),"",IF(S5=0,"",AC5/S5)) -> 0.056188393 | AF5: =IF(OR(K5="",G5=""),"",IF(J5=0,"",AC5/J5)) -> 0.081653893 | AG5: =IF(OR(K5="",G5=""),"",(J5+V5)/(1-(1+Settings!$B$10)*(IF(N5="",Settings!$B$5,N5)+IF(M5="",Settings!$B$11,M5))-IF(UPPER(O5)="Y",Settings!$B$9,0)-Settings!$B$13-Settings!$B$12)-N(L5)) -> 9.2538153 | AH5: =IF(OR(K5="",G5=""),"",(J5+V5+Settings!$B$15)/(1-(1+Settings!$B$10)*(IF(N5="",Settings!$B$5,N5)+IF(M5="",Settings!$B$11,M5))-IF(UPPER(O5)="Y",Settings!$B$9,0)-Settings!$B$13-Settings!$B$12)-N(L5)) -> 13.088269 | AI5: =IF(C5="","",IF(OR(ISNUMBER(SEARCH("amazon",C5)),ISNUMBER(SEARCH("walmart",C5)),ISNUMBER(SEARCH("aliexpress",C5)),ISNUMBER(SEARCH("temu",C5))),"⚠ Retail source — not allowed","✓ Wholesale / own stock")) -> ⚠ Retail source — not allowed | AJ5: =IF(OR(K5="",G5=""),"",IF(LEFT(AI5,1)="⚠","❌ SKIP",IF(AND(AC5>=Settings!$B$15,AF5>=Settings!$B$16,OR(R5="",N(R5)>=Settings!$B$17)),"✅ GO",IF(AC5>0,"⚠ CHECK","❌ SKIP")))) -> ❌ SKIP | AK5: EXAMPLE from your sheet — retail source
A6: =IF(B6="","",ROW()-4) -> 2 | B6: Kitchen Sink Sponge Holder, Stainless | C6: Alibaba | D6: https://www.alibaba.com/ | E6: https://www.ebay.com/ | F6: Kitchen Storage | G6: 4.2 | H6: 3.5 | I6: 0.3 | J6: =IF(G6="","",G6+N(H6)+N(I6)) -> 8 | K6: 19.99 | L6: 0 | O6: N | P6: 45 | Q6: 60 | R6: =IF(OR(P6="",Q6=""),"",P6/(P6+Q6)) -> 0.42857143 | S6: =IF(OR(K6="",G6=""),"",K6+N(L6)) -> 19.99 | T6: =IF(OR(K6="",G6=""),"",S6*Settings!$B$10) -> 1.3993 | U6: =IF(OR(K6="",G6=""),"",(S6+T6)*IF(N6="",Settings!$B$5,N6)) -> 2.9089448 | V6: =IF(OR(K6="",G6=""),"",IF(S6+T6<=Settings!$B$8,Settings!$B$6,Settings!$B$7)) -> 0.4 | W6: =IF(OR(K6="",G6=""),"",S6*IF(UPPER(O6)="Y",Settings!$B$9,0)) -> 0 | X6: =IF(OR(K6="",G6=""),"",(S6+T6)*IF(M6="",Settings!$B$11,M6)) -> 0.641679 | Y6: =IF(OR(K6="",G6=""),"",U6+V6+W6+X6) -> 3.9506238 | Z6: =IF(OR(K6="",G6=""),"",S6-Y6) -> 16.039376 | AA6: =IF(OR(K6="",G6=""),"",Z6*Settings!$B$12) -> 0.16039376 | AB6: =IF(OR(K6="",G6=""),"",S6*Settings!$B$13) -> 0.5997 | AC6: =IF(OR(K6="",G6=""),"",Z6-AA6-AB6-J6) -> 7.2792824 | AD6: =IF(OR(K6="",G6=""),"",AC6*Settings!$B$14) -> 2038.1991 | AE6: =IF(OR(K6="",G6=""),"",IF(S6=0,"",AC6/S6)) -> 0.36414619 | AF6: =IF(OR(K6="",G6=""),"",IF(J6=0,"",AC6/J6)) -> 0.9099103 | AG6: =IF(OR(K6="",G6=""),"",(J6+V6)/(1-(1+Settings!$B$10)*(IF(N6="",Settings!$B$5,N6)+IF(M6="",Settings!$B$11,M6))-IF(UPPER(O6)="Y",Settings!$B$9,0)-Settings!$B$13-Settings!$B$12)-N(L6)) -> 10.736471 | AH6: =IF(OR(K6="",G6=""),"",(J6+V6+Settings!$B$15)/(1-(1+Settings!$B$10)*(IF(N6="",Settings!$B$5,N6)+IF(M6="",Settings!$B$11,M6))-IF(UPPER(O6)="Y",Settings!$B$9,0)-Settings!$B$13-Settings!$B$12)-N(L6)) -> 14.570925 | AI6: =IF(C6="","",IF(OR(ISNUMBER(SEARCH("amazon",C6)),ISNUMBER(SEARCH("walmart",C6)),ISNUMBER(SEARCH("aliexpress",C6)),ISNUMBER(SEARCH("temu",C6))),"⚠ Retail source — not allowed","✓ Wholesale / own stock")) -> ✓ Wholesale / own stock | AJ6: =IF(OR(K6="",G6=""),"",IF(LEFT(AI6,1)="⚠","❌ SKIP",IF(AND(AC6>=Settings!$B$15,AF6>=Settings!$B$16,OR(R6="",N(R6)>=Settings!$B$17)),"✅ GO",IF(AC6>0,"⚠ CHECK","❌ SKIP")))) -> ✅ GO | AK6: EXAMPLE — replace with your own
A7: =IF(B7="","",ROW()-4) -> 3 | B7: Stainless Steel Lemon Squeezer | C7: Alibaba | D7: https://www.alibaba.com/ | E7: https://www.ebay.com/ | F7: Manual Juicers | G7: 10.15 | H7: 0 | I7: 0 | J7: =IF(G7="","",G7+N(H7)+N(I7)) -> 10.15 | K7: 22.99 | L7: 0 | M7: 0.05 | O7: N | P7: 30 | Q7: 55 | R7: =IF(OR(P7="",Q7=""),"",P7/(P7+Q7)) -> 0.35294118 | S7: =IF(OR(K7="",G7=""),"",K7+N(L7)) -> 22.99 | T7: =IF(OR(K7="",G7=""),"",S7*Settings!$B$10) -> 1.6093 | U7: =IF(OR(K7="",G7=""),"",(S7+T7)*IF(N7="",Settings!$B$5,N7)) -> 3.3455048 | V7: =IF(OR(K7="",G7=""),"",IF(S7+T7<=Settings!$B$8,Settings!$B$6,Settings!$B$7)) -> 0.4 | W7: =IF(OR(K7="",G7=""),"",S7*IF(UPPER(O7)="Y",Settings!$B$9,0)) -> 0 | X7: =IF(OR(K7="",G7=""),"",(S7+T7)*IF(M7="",Settings!$B$11,M7)) -> 1.229965 | Y7: =IF(OR(K7="",G7=""),"",U7+V7+W7+X7) -> 4.9754698 | Z7: =IF(OR(K7="",G7=""),"",S7-Y7) -> 18.01453 | AA7: =IF(OR(K7="",G7=""),"",Z7*Settings!$B$12) -> 0.1801453 | AB7: =IF(OR(K7="",G7=""),"",S7*Settings!$B$13) -> 0.6897 | AC7: =IF(OR(K7="",G7=""),"",Z7-AA7-AB7-J7) -> 6.9946849 | AD7: =IF(OR(K7="",G7=""),"",AC7*Settings!$B$14) -> 1958.5118 | AE7: =IF(OR(K7="",G7=""),"",IF(S7=0,"",AC7/S7)) -> 0.30424902 | AF7: =IF(OR(K7="",G7=""),"",IF(J7=0,"",AC7/J7)) -> 0.68913152 | AG7: =IF(OR(K7="",G7=""),"",(J7+V7)/(1-(1+Settings!$B$10)*(IF(N7="",Settings!$B$5,N7)+IF(M7="",Settings!$B$11,M7))-IF(UPPER(O7)="Y",Settings!$B$9,0)-Settings!$B$13-Settings!$B$12)-N(L7)) -> 13.863702 | AH7: =IF(OR(K7="",G7=""),"",(J7+V7+Settings!$B$15)/(1-(1+Settings!$B$10)*(IF(N7="",Settings!$B$5,N7)+IF(M7="",Settings!$B$11,M7))-IF(UPPER(O7)="Y",Settings!$B$9,0)-Settings!$B$13-Settings!$B$12)-N(L7)) -> 17.805987 | AI7: =IF(C7="","",IF(OR(ISNUMBER(SEARCH("amazon",C7)),ISNUMBER(SEARCH("walmart",C7)),ISNUMBER(SEARCH("aliexpress",C7)),ISNUMBER(SEARCH("temu",C7))),"⚠ Retail source — not allowed","✓ Wholesale / own stock")) -> ✓ Wholesale / own stock | AJ7: =IF(OR(K7="",G7=""),"",IF(LEFT(AI7,1)="⚠","❌ SKIP",IF(AND(AC7>=Settings!$B$15,AF7>=Settings!$B$16,OR(R7="",N(R7)>=Settings!$B$17)),"✅ GO",IF(AC7>0,"⚠ CHECK","❌ SKIP")))) -> ⚠ CHECK | AK7: EXAMPLE — category blocked for PK accounts
A8: =IF(B8="","",ROW()-4) | J8: =IF(G8="","",G8+N(H8)+N(I8)) | R8: =IF(OR(P8="",Q8=""),"",P8/(P8+Q8)) | S8: =IF(OR(K8="",G8=""),"",K8+N(L8)) | T8: =IF(OR(K8="",G8=""),"",S8*Settings!$B$10) | U8: =IF(OR(K8="",G8=""),"",(S8+T8)*IF(N8="",Settings!$B$5,N8)) | V8: =IF(OR(K8="",G8=""),"",IF(S8+T8<=Settings!$B$8,Settings!$B$6,Settings!$B$7)) | W8: =IF(OR(K8="",G8=""),"",S8*IF(UPPER(O8)="Y",Settings!$B$9,0)) | X8: =IF(OR(K8="",G8=""),"",(S8+T8)*IF(M8="",Settings!$B$11,M8)) | Y8: =IF(OR(K8="",G8=""),"",U8+V8+W8+X8) | Z8: =IF(OR(K8="",G8=""),"",S8-Y8) | AA8: =IF(OR(K8="",G8=""),"",Z8*Settings!$B$12) | AB8: =IF(OR(K8="",G8=""),"",S8*Settings!$B$13) | AC8: =IF(OR(K8="",G8=""),"",Z8-AA8-AB8-J8) | AD8: =IF(OR(K8="",G8=""),"",AC8*Settings!$B$14) | AE8: =IF(OR(K8="",G8=""),"",IF(S8=0,"",AC8/S8)) | AF8: =IF(OR(K8="",G8=""),"",IF(J8=0,"",AC8/J8)) | AG8: =IF(OR(K8="",G8=""),"",(J8+V8)/(1-(1+Settings!$B$10)*(IF(N8="",Settings!$B$5,N8)+IF(M8="",Settings!$B$11,M8))-IF(UPPER(O8)="Y",Settings!$B$9,0)-Settings!$B$13-Settings!$B$12)-N(L8)) | AH8: =IF(OR(K8="",G8=""),"",(J8+V8+Settings!$B$15)/(1-(1+Settings!$B$10)*(IF(N8="",Settings!$B$5,N8)+IF(M8="",Settings!$B$11,M8))-IF(UPPER(O8)="Y",Settings!$B$9,0)-Settings!$B$13-Settings!$B$12)-N(L8)) | AI8: =IF(C8="","",IF(OR(ISNUMBER(SEARCH("amazon",C8)),ISNUMBER(SEARCH("walmart",C8)),ISNUMBER(SEARCH("aliexpress",C8)),ISNUMBER(SEARCH("temu",C8))),"⚠ Retail source — not allowed","✓ Wholesale / own stock")) | AJ8: =IF(OR(K8="",G8=""),"",IF(LEFT(AI8,1)="⚠","❌ SKIP",IF(AND(AC8>=Settings!$B$15,AF8>=Settings!$B$16,OR(R8="",N(R8)>=Settings!$B$17)),"✅ GO",IF(AC8>0,"⚠ CHECK","❌ SKIP"))))
A9: =IF(B9="","",ROW()-4) | J9: =IF(G9="","",G9+N(H9)+N(I9)) | R9: =IF(OR(P9="",Q9=""),"",P9/(P9+Q9)) | S9: =IF(OR(K9="",G9=""),"",K9+N(L9)) | T9: =IF(OR(K9="",G9=""),"",S9*Settings!$B$10) | U9: =IF(OR(K9="",G9=""),"",(S9+T9)*IF(N9="",Settings!$B$5,N9)) | V9: =IF(OR(K9="",G9=""),"",IF(S9+T9<=Settings!$B$8,Settings!$B$6,Settings!$B$7)) | W9: =IF(OR(K9="",G9=""),"",S9*IF(UPPER(O9)="Y",Settings!$B$9,0)) | X9: =IF(OR(K9="",G9=""),"",(S9+T9)*IF(M9="",Settings!$B$11,M9)) | Y9: =IF(OR(K9="",G9=""),"",U9+V9+W9+X9) | Z9: =IF(OR(K9="",G9=""),"",S9-Y9) | AA9: =IF(OR(K9="",G9=""),"",Z9*Settings!$B$12) | AB9: =IF(OR(K9="",G9=""),"",S9*Settings!$B$13) | AC9: =IF(OR(K9="",G9=""),"",Z9-AA9-AB9-J9) | AD9: =IF(OR(K9="",G9=""),"",AC9*Settings!$B$14) | AE9: =IF(OR(K9="",G9=""),"",IF(S9=0,"",AC9/S9)) | AF9: =IF(OR(K9="",G9=""),"",IF(J9=0,"",AC9/J9)) | AG9: =IF(OR(K9="",G9=""),"",(J9+V9)/(1-(1+Settings!$B$10)*(IF(N9="",Settings!$B$5,N9)+IF(M9="",Settings!$B$11,M9))-IF(UPPER(O9)="Y",Settings!$B$9,0)-Settings!$B$13-Settings!$B$12)-N(L9)) | AH9: =IF(OR(K9="",G9=""),"",(J9+V9+Settings!$B$15)/(1-(1+Settings!$B$10)*(IF(N9="",Settings!$B$5,N9)+IF(M9="",Settings!$B$11,M9))-IF(UPPER(O9)="Y",Settings!$B$9,0)-Settings!$B$13-Settings!$B$12)-N(L9)) | AI9: =IF(C9="","",IF(OR(ISNUMBER(SEARCH("amazon",C9)),ISNUMBER(SEARCH("walmart",C9)),ISNUMBER(SEARCH("aliexpress",C9)),ISNUMBER(SEARCH("temu",C9))),"⚠ Retail source — not allowed","✓ Wholesale / own stock")) | AJ9: =IF(OR(K9="",G9=""),"",IF(LEFT(AI9,1)="⚠","❌ SKIP",IF(AND(AC9>=Settings!$B$15,AF9>=Settings!$B$16,OR(R9="",N(R9)>=Settings!$B$17)),"✅ GO",IF(AC9>0,"⚠ CHECK","❌ SKIP"))))
A10: =IF(B10="","",ROW()-4) | J10: =IF(G10="","",G10+N(H10)+N(I10)) | R10: =IF(OR(P10="",Q10=""),"",P10/(P10+Q10)) | S10: =IF(OR(K10="",G10=""),"",K10+N(L10)) | T10: =IF(OR(K10="",G10=""),"",S10*Settings!$B$10) | U10: =IF(OR(K10="",G10=""),"",(S10+T10)*IF(N10="",Settings!$B$5,N10)) | V10: =IF(OR(K10="",G10=""),"",IF(S10+T10<=Settings!$B$8,Settings!$B$6,Settings!$B$7)) | W10: =IF(OR(K10="",G10=""),"",S10*IF(UPPER(O10)="Y",Settings!$B$9,0)) | X10: =IF(OR(K10="",G10=""),"",(S10+T10)*IF(M10="",Settings!$B$11,M10)) | Y10: =IF(OR(K10="",G10=""),"",U10+V10+W10+X10) | Z10: =IF(OR(K10="",G10=""),"",S10-Y10) | AA10: =IF(OR(K10="",G10=""),"",Z10*Settings!$B$12) | AB10: =IF(OR(K10="",G10=""),"",S10*Settings!$B$13) | AC10: =IF(OR(K10="",G10=""),"",Z10-AA10-AB10-J10) | AD10: =IF(OR(K10="",G10=""),"",AC10*Settings!$B$14) | AE10: =IF(OR(K10="",G10=""),"",IF(S10=0,"",AC10/S10)) | AF10: =IF(OR(K10="",G10=""),"",IF(J10=0,"",AC10/J10)) | AG10: =IF(OR(K10="",G10=""),"",(J10+V10)/(1-(1+Settings!$B$10)*(IF(N10="",Settings!$B$5,N10)+IF(M10="",Settings!$B$11,M10))-IF(UPPER(O10)="Y",Settings!$B$9,0)-Settings!$B$13-Settings!$B$12)-N(L10)) | AH10: =IF(OR(K10="",G10=""),"",(J10+V10+Settings!$B$15)/(1-(1+Settings!$B$10)*(IF(N10="",Settings!$B$5,N10)+IF(M10="",Settings!$B$11,M10))-IF(UPPER(O10)="Y",Settings!$B$9,0)-Settings!$B$13-Settings!$B$12)-N(L10)) | AI10: =IF(C10="","",IF(OR(ISNUMBER(SEARCH("amazon",C10)),ISNUMBER(SEARCH("walmart",C10)),ISNUMBER(SEARCH("aliexpress",C10)),ISNUMBER(SEARCH("temu",C10))),"⚠ Retail source — not allowed","✓ Wholesale / own stock")) | AJ10: =IF(OR(K10="",G10=""),"",IF(LEFT(AI10,1)="⚠","❌ SKIP",IF(AND(AC10>=Settings!$B$15,AF10>=Settings!$B$16,OR(R10="",N(R10)>=Settings!$B$17)),"✅ GO",IF(AC10>0,"⚠ CHECK","❌ SKIP"))))
A11: =IF(B11="","",ROW()-4) | J11: =IF(G11="","",G11+N(H11)+N(I11)) | R11: =IF(OR(P11="",Q11=""),"",P11/(P11+Q11)) | S11: =IF(OR(K11="",G11=""),"",K11+N(L11)) | T11: =IF(OR(K11="",G11=""),"",S11*Settings!$B$10) | U11: =IF(OR(K11="",G11=""),"",(S11+T11)*IF(N11="",Settings!$B$5,N11)) | V11: =IF(OR(K11="",G11=""),"",IF(S11+T11<=Settings!$B$8,Settings!$B$6,Settings!$B$7)) | W11: =IF(OR(K11="",G11=""),"",S11*IF(UPPER(O11)="Y",Settings!$B$9,0)) | X11: =IF(OR(K11="",G11=""),"",(S11+T11)*IF(M11="",Settings!$B$11,M11)) | Y11: =IF(OR(K11="",G11=""),"",U11+V11+W11+X11) | Z11: =IF(OR(K11="",G11=""),"",S11-Y11) | AA11: =IF(OR(K11="",G11=""),"",Z11*Settings!$B$12) | AB11: =IF(OR(K11="",G11=""),"",S11*Settings!$B$13) | AC11: =IF(OR(K11="",G11=""),"",Z11-AA11-AB11-J11) | AD11: =IF(OR(K11="",G11=""),"",AC11*Settings!$B$14) | AE11: =IF(OR(K11="",G11=""),"",IF(S11=0,"",AC11/S11)) | AF11: =IF(OR(K11="",G11=""),"",IF(J11=0,"",AC11/J11)) | AG11: =IF(OR(K11="",G11=""),"",(J11+V11)/(1-(1+Settings!$B$10)*(IF(N11="",Settings!$B$5,N11)+IF(M11="",Settings!$B$11,M11))-IF(UPPER(O11)="Y",Settings!$B$9,0)-Settings!$B$13-Settings!$B$12)-N(L11)) | AH11: =IF(OR(K11="",G11=""),"",(J11+V11+Settings!$B$15)/(1-(1+Settings!$B$10)*(IF(N11="",Settings!$B$5,N11)+IF(M11="",Settings!$B$11,M11))-IF(UPPER(O11)="Y",Settings!$B$9,0)-Settings!$B$13-Settings!$B$12)-N(L11)) | AI11: =IF(C11="","",IF(OR(ISNUMBER(SEARCH("amazon",C11)),ISNUMBER(SEARCH("walmart",C11)),ISNUMBER(SEARCH("aliexpress",C11)),ISNUMBER(SEARCH("temu",C11))),"⚠ Retail source — not allowed","✓ Wholesale / own stock")) | AJ11: =IF(OR(K11="",G11=""),"",IF(LEFT(AI11,1)="⚠","❌ SKIP",IF(AND(AC11>=Settings!$B$15,AF11>=Settings!$B$16,OR(R11="",N(R11)>=Settings!$B$17)),"✅ GO",IF(AC11>0,"⚠ CHECK","❌ SKIP"))))
A12: =IF(B12="","",ROW()-4) | J12: =IF(G12="","",G12+N(H12)+N(I12)) | R12: =IF(OR(P12="",Q12=""),"",P12/(P12+Q12)) | S12: =IF(OR(K12="",G12=""),"",K12+N(L12)) | T12: =IF(OR(K12="",G12=""),"",S12*Settings!$B$10) | U12: =IF(OR(K12="",G12=""),"",(S12+T12)*IF(N12="",Settings!$B$5,N12)) | V12: =IF(OR(K12="",G12=""),"",IF(S12+T12<=Settings!$B$8,Settings!$B$6,Settings!$B$7)) | W12: =IF(OR(K12="",G12=""),"",S12*IF(UPPER(O12)="Y",Settings!$B$9,0)) | X12: =IF(OR(K12="",G12=""),"",(S12+T12)*IF(M12="",Settings!$B$11,M12)) | Y12: =IF(OR(K12="",G12=""),"",U12+V12+W12+X12) | Z12: =IF(OR(K12="",G12=""),"",S12-Y12) | AA12: =IF(OR(K12="",G12=""),"",Z12*Settings!$B$12) | AB12: =IF(OR(K12="",G12=""),"",S12*Settings!$B$13) | AC12: =IF(OR(K12="",G12=""),"",Z12-AA12-AB12-J12) | AD12: =IF(OR(K12="",G12=""),"",AC12*Settings!$B$14) | AE12: =IF(OR(K12="",G12=""),"",IF(S12=0,"",AC12/S12)) | AF12: =IF(OR(K12="",G12=""),"",IF(J12=0,"",AC12/J12)) | AG12: =IF(OR(K12="",G12=""),"",(J12+V12)/(1-(1+Settings!$B$10)*(IF(N12="",Settings!$B$5,N12)+IF(M12="",Settings!$B$11,M12))-IF(UPPER(O12)="Y",Settings!$B$9,0)-Settings!$B$13-Settings!$B$12)-N(L12)) | AH12: =IF(OR(K12="",G12=""),"",(J12+V12+Settings!$B$15)/(1-(1+Settings!$B$10)*(IF(N12="",Settings!$B$5,N12)+IF(M12="",Settings!$B$11,M12))-IF(UPPER(O12)="Y",Settings!$B$9,0)-Settings!$B$13-Settings!$B$12)-N(L12)) | AI12: =IF(C12="","",IF(OR(ISNUMBER(SEARCH("amazon",C12)),ISNUMBER(SEARCH("walmart",C12)),ISNUMBER(SEARCH("aliexpress",C12)),ISNUMBER(SEARCH("temu",C12))),"⚠ Retail source — not allowed","✓ Wholesale / own stock")) | AJ12: =IF(OR(K12="",G12=""),"",IF(LEFT(AI12,1)="⚠","❌ SKIP",IF(AND(AC12>=Settings!$B$15,AF12>=Settings!$B$16,OR(R12="",N(R12)>=Settings!$B$17)),"✅ GO",IF(AC12>0,"⚠ CHECK","❌ SKIP"))))
A13: =IF(B13="","",ROW()-4) | J13: =IF(G13="","",G13+N(H13)+N(I13)) | R13: =IF(OR(P13="",Q13=""),"",P13/(P13+Q13)) | S13: =IF(OR(K13="",G13=""),"",K13+N(L13)) | T13: =IF(OR(K13="",G13=""),"",S13*Settings!$B$10) | U13: =IF(OR(K13="",G13=""),"",(S13+T13)*IF(N13="",Settings!$B$5,N13)) | V13: =IF(OR(K13="",G13=""),"",IF(S13+T13<=Settings!$B$8,Settings!$B$6,Settings!$B$7)) | W13: =IF(OR(K13="",G13=""),"",S13*IF(UPPER(O13)="Y",Settings!$B$9,0)) | X13: =IF(OR(K13="",G13=""),"",(S13+T13)*IF(M13="",Settings!$B$11,M13)) | Y13: =IF(OR(K13="",G13=""),"",U13+V13+W13+X13) | Z13: =IF(OR(K13="",G13=""),"",S13-Y13) | AA13: =IF(OR(K13="",G13=""),"",Z13*Settings!$B$12) | AB13: =IF(OR(K13="",G13=""),"",S13*Settings!$B$13) | AC13: =IF(OR(K13="",G13=""),"",Z13-AA13-AB13-J13) | AD13: =IF(OR(K13="",G13=""),"",AC13*Settings!$B$14) | AE13: =IF(OR(K13="",G13=""),"",IF(S13=0,"",AC13/S13)) | AF13: =IF(OR(K13="",G13=""),"",IF(J13=0,"",AC13/J13)) | AG13: =IF(OR(K13="",G13=""),"",(J13+V13)/(1-(1+Settings!$B$10)*(IF(N13="",Settings!$B$5,N13)+IF(M13="",Settings!$B$11,M13))-IF(UPPER(O13)="Y",Settings!$B$9,0)-Settings!$B$13-Settings!$B$12)-N(L13)) | AH13: =IF(OR(K13="",G13=""),"",(J13+V13+Settings!$B$15)/(1-(1+Settings!$B$10)*(IF(N13="",Settings!$B$5,N13)+IF(M13="",Settings!$B$11,M13))-IF(UPPER(O13)="Y",Settings!$B$9,0)-Settings!$B$13-Settings!$B$12)-N(L13)) | AI13: =IF(C13="","",IF(OR(ISNUMBER(SEARCH("amazon",C13)),ISNUMBER(SEARCH("walmart",C13)),ISNUMBER(SEARCH("aliexpress",C13)),ISNUMBER(SEARCH("temu",C13))),"⚠ Retail source — not allowed","✓ Wholesale / own stock")) | AJ13: =IF(OR(K13="",G13=""),"",IF(LEFT(AI13,1)="⚠","❌ SKIP",IF(AND(AC13>=Settings!$B$15,AF13>=Settings!$B$16,OR(R13="",N(R13)>=Settings!$B$17)),"✅ GO",IF(AC13>0,"⚠ CHECK","❌ SKIP"))))
A14: =IF(B14="","",ROW()-4) | J14: =IF(G14="","",G14+N(H14)+N(I14)) | R14: =IF(OR(P14="",Q14=""),"",P14/(P14+Q14)) | S14: =IF(OR(K14="",G14=""),"",K14+N(L14)) | T14: =IF(OR(K14="",G14=""),"",S14*Settings!$B$10) | U14: =IF(OR(K14="",G14=""),"",(S14+T14)*IF(N14="",Settings!$B$5,N14)) | V14: =IF(OR(K14="",G14=""),"",IF(S14+T14<=Settings!$B$8,Settings!$B$6,Settings!$B$7)) | W14: =IF(OR(K14="",G14=""),"",S14*IF(UPPER(O14)="Y",Settings!$B$9,0)) | X14: =IF(OR(K14="",G14=""),"",(S14+T14)*IF(M14="",Settings!$B$11,M14)) | Y14: =IF(OR(K14="",G14=""),"",U14+V14+W14+X14) | Z14: =IF(OR(K14="",G14=""),"",S14-Y14) | AA14: =IF(OR(K14="",G14=""),"",Z14*Settings!$B$12) | AB14: =IF(OR(K14="",G14=""),"",S14*Settings!$B$13) | AC14: =IF(OR(K14="",G14=""),"",Z14-AA14-AB14-J14) | AD14: =IF(OR(K14="",G14=""),"",AC14*Settings!$B$14) | AE14: =IF(OR(K14="",G14=""),"",IF(S14=0,"",AC14/S14)) | AF14: =IF(OR(K14="",G14=""),"",IF(J14=0,"",AC14/J14)) | AG14: =IF(OR(K14="",G14=""),"",(J14+V14)/(1-(1+Settings!$B$10)*(IF(N14="",Settings!$B$5,N14)+IF(M14="",Settings!$B$11,M14))-IF(UPPER(O14)="Y",Settings!$B$9,0)-Settings!$B$13-Settings!$B$12)-N(L14)) | AH14: =IF(OR(K14="",G14=""),"",(J14+V14+Settings!$B$15)/(1-(1+Settings!$B$10)*(IF(N14="",Settings!$B$5,N14)+IF(M14="",Settings!$B$11,M14))-IF(UPPER(O14)="Y",Settings!$B$9,0)-Settings!$B$13-Settings!$B$12)-N(L14)) | AI14: =IF(C14="","",IF(OR(ISNUMBER(SEARCH("amazon",C14)),ISNUMBER(SEARCH("walmart",C14)),ISNUMBER(SEARCH("aliexpress",C14)),ISNUMBER(SEARCH("temu",C14))),"⚠ Retail source — not allowed","✓ Wholesale / own stock")) | AJ14: =IF(OR(K14="",G14=""),"",IF(LEFT(AI14,1)="⚠","❌ SKIP",IF(AND(AC14>=Settings!$B$15,AF14>=Settings!$B$16,OR(R14="",N(R14)>=Settings!$B$17)),"✅ GO",IF(AC14>0,"⚠ CHECK","❌ SKIP"))))
A15: =IF(B15="","",ROW()-4) | J15: =IF(G15="","",G15+N(H15)+N(I15)) | R15: =IF(OR(P15="",Q15=""),"",P15/(P15+Q15)) | S15: =IF(OR(K15="",G15=""),"",K15+N(L15)) | T15: =IF(OR(K15="",G15=""),"",S15*Settings!$B$10) | U15: =IF(OR(K15="",G15=""),"",(S15+T15)*IF(N15="",Settings!$B$5,N15)) | V15: =IF(OR(K15="",G15=""),"",IF(S15+T15<=Settings!$B$8,Settings!$B$6,Settings!$B$7)) | W15: =IF(OR(K15="",G15=""),"",S15*IF(UPPER(O15)="Y",Settings!$B$9,0)) | X15: =IF(OR(K15="",G15=""),"",(S15+T15)*IF(M15="",Settings!$B$11,M15)) | Y15: =IF(OR(K15="",G15=""),"",U15+V15+W15+X15) | Z15: =IF(OR(K15="",G15=""),"",S15-Y15) | AA15: =IF(OR(K15="",G15=""),"",Z15*Settings!$B$12) | AB15: =IF(OR(K15="",G15=""),"",S15*Settings!$B$13) | AC15: =IF(OR(K15="",G15=""),"",Z15-AA15-AB15-J15) | AD15: =IF(OR(K15="",G15=""),"",AC15*Settings!$B$14) | AE15: =IF(OR(K15="",G15=""),"",IF(S15=0,"",AC15/S15)) | AF15: =IF(OR(K15="",G15=""),"",IF(J15=0,"",AC15/J15)) | AG15: =IF(OR(K15="",G15=""),"",(J15+V15)/(1-(1+Settings!$B$10)*(IF(N15="",Settings!$B$5,N15)+IF(M15="",Settings!$B$11,M15))-IF(UPPER(O15)="Y",Settings!$B$9,0)-Settings!$B$13-Settings!$B$12)-N(L15)) | AH15: =IF(OR(K15="",G15=""),"",(J15+V15+Settings!$B$15)/(1-(1+Settings!$B$10)*(IF(N15="",Settings!$B$5,N15)+IF(M15="",Settings!$B$11,M15))-IF(UPPER(O15)="Y",Settings!$B$9,0)-Settings!$B$13-Settings!$B$12)-N(L15)) | AI15: =IF(C15="","",IF(OR(ISNUMBER(SEARCH("amazon",C15)),ISNUMBER(SEARCH("walmart",C15)),ISNUMBER(SEARCH("aliexpress",C15)),ISNUMBER(SEARCH("temu",C15))),"⚠ Retail source — not allowed","✓ Wholesale / own stock")) | AJ15: =IF(OR(K15="",G15=""),"",IF(LEFT(AI15,1)="⚠","❌ SKIP",IF(AND(AC15>=Settings!$B$15,AF15>=Settings!$B$16,OR(R15="",N(R15)>=Settings!$B$17)),"✅ GO",IF(AC15>0,"⚠ CHECK","❌ SKIP"))))
A16: =IF(B16="","",ROW()-4) | J16: =IF(G16="","",G16+N(H16)+N(I16)) | R16: =IF(OR(P16="",Q16=""),"",P16/(P16+Q16)) | S16: =IF(OR(K16="",G16=""),"",K16+N(L16)) | T16: =IF(OR(K16="",G16=""),"",S16*Settings!$B$10) | U16: =IF(OR(K16="",G16=""),"",(S16+T16)*IF(N16="",Settings!$B$5,N16)) | V16: =IF(OR(K16="",G16=""),"",IF(S16+T16<=Settings!$B$8,Settings!$B$6,Settings!$B$7)) | W16: =IF(OR(K16="",G16=""),"",S16*IF(UPPER(O16)="Y",Settings!$B$9,0)) | X16: =IF(OR(K16="",G16=""),"",(S16+T16)*IF(M16="",Settings!$B$11,M16)) | Y16: =IF(OR(K16="",G16=""),"",U16+V16+W16+X16) | Z16: =IF(OR(K16="",G16=""),"",S16-Y16) | AA16: =IF(OR(K16="",G16=""),"",Z16*Settings!$B$12) | AB16: =IF(OR(K16="",G16=""),"",S16*Settings!$B$13) | AC16: =IF(OR(K16="",G16=""),"",Z16-AA16-AB16-J16) | AD16: =IF(OR(K16="",G16=""),"",AC16*Settings!$B$14) | AE16: =IF(OR(K16="",G16=""),"",IF(S16=0,"",AC16/S16)) | AF16: =IF(OR(K16="",G16=""),"",IF(J16=0,"",AC16/J16)) | AG16: =IF(OR(K16="",G16=""),"",(J16+V16)/(1-(1+Settings!$B$10)*(IF(N16="",Settings!$B$5,N16)+IF(M16="",Settings!$B$11,M16))-IF(UPPER(O16)="Y",Settings!$B$9,0)-Settings!$B$13-Settings!$B$12)-N(L16)) | AH16: =IF(OR(K16="",G16=""),"",(J16+V16+Settings!$B$15)/(1-(1+Settings!$B$10)*(IF(N16="",Settings!$B$5,N16)+IF(M16="",Settings!$B$11,M16))-IF(UPPER(O16)="Y",Settings!$B$9,0)-Settings!$B$13-Settings!$B$12)-N(L16)) | AI16: =IF(C16="","",IF(OR(ISNUMBER(SEARCH("amazon",C16)),ISNUMBER(SEARCH("walmart",C16)),ISNUMBER(SEARCH("aliexpress",C16)),ISNUMBER(SEARCH("temu",C16))),"⚠ Retail source — not allowed","✓ Wholesale / own stock")) | AJ16: =IF(OR(K16="",G16=""),"",IF(LEFT(AI16,1)="⚠","❌ SKIP",IF(AND(AC16>=Settings!$B$15,AF16>=Settings!$B$16,OR(R16="",N(R16)>=Settings!$B$17)),"✅ GO",IF(AC16>0,"⚠ CHECK","❌ SKIP"))))
A17: =IF(B17="","",ROW()-4) | J17: =IF(G17="","",G17+N(H17)+N(I17)) | R17: =IF(OR(P17="",Q17=""),"",P17/(P17+Q17)) | S17: =IF(OR(K17="",G17=""),"",K17+N(L17)) | T17: =IF(OR(K17="",G17=""),"",S17*Settings!$B$10) | U17: =IF(OR(K17="",G17=""),"",(S17+T17)*IF(N17="",Settings!$B$5,N17)) | V17: =IF(OR(K17="",G17=""),"",IF(S17+T17<=Settings!$B$8,Settings!$B$6,Settings!$B$7)) | W17: =IF(OR(K17="",G17=""),"",S17*IF(UPPER(O17)="Y",Settings!$B$9,0)) | X17: =IF(OR(K17="",G17=""),"",(S17+T17)*IF(M17="",Settings!$B$11,M17)) | Y17: =IF(OR(K17="",G17=""),"",U17+V17+W17+X17) | Z17: =IF(OR(K17="",G17=""),"",S17-Y17) | AA17: =IF(OR(K17="",G17=""),"",Z17*Settings!$B$12) | AB17: =IF(OR(K17="",G17=""),"",S17*Settings!$B$13) | AC17: =IF(OR(K17="",G17=""),"",Z17-AA17-AB17-J17) | AD17: =IF(OR(K17="",G17=""),"",AC17*Settings!$B$14) | AE17: =IF(OR(K17="",G17=""),"",IF(S17=0,"",AC17/S17)) | AF17: =IF(OR(K17="",G17=""),"",IF(J17=0,"",AC17/J17)) | AG17: =IF(OR(K17="",G17=""),"",(J17+V17)/(1-(1+Settings!$B$10)*(IF(N17="",Settings!$B$5,N17)+IF(M17="",Settings!$B$11,M17))-IF(UPPER(O17)="Y",Settings!$B$9,0)-Settings!$B$13-Settings!$B$12)-N(L17)) | AH17: =IF(OR(K17="",G17=""),"",(J17+V17+Settings!$B$15)/(1-(1+Settings!$B$10)*(IF(N17="",Settings!$B$5,N17)+IF(M17="",Settings!$B$11,M17))-IF(UPPER(O17)="Y",Settings!$B$9,0)-Settings!$B$13-Settings!$B$12)-N(L17)) | AI17: =IF(C17="","",IF(OR(ISNUMBER(SEARCH("amazon",C17)),ISNUMBER(SEARCH("walmart",C17)),ISNUMBER(SEARCH("aliexpress",C17)),ISNUMBER(SEARCH("temu",C17))),"⚠ Retail source — not allowed","✓ Wholesale / own stock")) | AJ17: =IF(OR(K17="",G17=""),"",IF(LEFT(AI17,1)="⚠","❌ SKIP",IF(AND(AC17>=Settings!$B$15,AF17>=Settings!$B$16,OR(R17="",N(R17)>=Settings!$B$17)),"✅ GO",IF(AC17>0,"⚠ CHECK","❌ SKIP"))))
A18: =IF(B18="","",ROW()-4) | J18: =IF(G18="","",G18+N(H18)+N(I18)) | R18: =IF(OR(P18="",Q18=""),"",P18/(P18+Q18)) | S18: =IF(OR(K18="",G18=""),"",K18+N(L18)) | T18: =IF(OR(K18="",G18=""),"",S18*Settings!$B$10) | U18: =IF(OR(K18="",G18=""),"",(S18+T18)*IF(N18="",Settings!$B$5,N18)) | V18: =IF(OR(K18="",G18=""),"",IF(S18+T18<=Settings!$B$8,Settings!$B$6,Settings!$B$7)) | W18: =IF(OR(K18="",G18=""),"",S18*IF(UPPER(O18)="Y",Settings!$B$9,0)) | X18: =IF(OR(K18="",G18=""),"",(S18+T18)*IF(M18="",Settings!$B$11,M18)) | Y18: =IF(OR(K18="",G18=""),"",U18+V18+W18+X18) | Z18: =IF(OR(K18="",G18=""),"",S18-Y18) | AA18: =IF(OR(K18="",G18=""),"",Z18*Settings!$B$12) | AB18: =IF(OR(K18="",G18=""),"",S18*Settings!$B$13) | AC18: =IF(OR(K18="",G18=""),"",Z18-AA18-AB18-J18) | AD18: =IF(OR(K18="",G18=""),"",AC18*Settings!$B$14) | AE18: =IF(OR(K18="",G18=""),"",IF(S18=0,"",AC18/S18)) | AF18: =IF(OR(K18="",G18=""),"",IF(J18=0,"",AC18/J18)) | AG18: =IF(OR(K18="",G18=""),"",(J18+V18)/(1-(1+Settings!$B$10)*(IF(N18="",Settings!$B$5,N18)+IF(M18="",Settings!$B$11,M18))-IF(UPPER(O18)="Y",Settings!$B$9,0)-Settings!$B$13-Settings!$B$12)-N(L18)) | AH18: =IF(OR(K18="",G18=""),"",(J18+V18+Settings!$B$15)/(1-(1+Settings!$B$10)*(IF(N18="",Settings!$B$5,N18)+IF(M18="",Settings!$B$11,M18))-IF(UPPER(O18)="Y",Settings!$B$9,0)-Settings!$B$13-Settings!$B$12)-N(L18)) | AI18: =IF(C18="","",IF(OR(ISNUMBER(SEARCH("amazon",C18)),ISNUMBER(SEARCH("walmart",C18)),ISNUMBER(SEARCH("aliexpress",C18)),ISNUMBER(SEARCH("temu",C18))),"⚠ Retail source — not allowed","✓ Wholesale / own stock")) | AJ18: =IF(OR(K18="",G18=""),"",IF(LEFT(AI18,1)="⚠","❌ SKIP",IF(AND(AC18>=Settings!$B$15,AF18>=Settings!$B$16,OR(R18="",N(R18)>=Settings!$B$17)),"✅ GO",IF(AC18>0,"⚠ CHECK","❌ SKIP"))))
A19: =IF(B19="","",ROW()-4) | J19: =IF(G19="","",G19+N(H19)+N(I19)) | R19: =IF(OR(P19="",Q19=""),"",P19/(P19+Q19)) | S19: =IF(OR(K19="",G19=""),"",K19+N(L19)) | T19: =IF(OR(K19="",G19=""),"",S19*Settings!$B$10) | U19: =IF(OR(K19="",G19=""),"",(S19+T19)*IF(N19="",Settings!$B$5,N19)) | V19: =IF(OR(K19="",G19=""),"",IF(S19+T19<=Settings!$B$8,Settings!$B$6,Settings!$B$7)) | W19: =IF(OR(K19="",G19=""),"",S19*IF(UPPER(O19)="Y",Settings!$B$9,0)) | X19: =IF(OR(K19="",G19=""),"",(S19+T19)*IF(M19="",Settings!$B$11,M19)) | Y19: =IF(OR(K19="",G19=""),"",U19+V19+W19+X19) | Z19: =IF(OR(K19="",G19=""),"",S19-Y19) | AA19: =IF(OR(K19="",G19=""),"",Z19*Settings!$B$12) | AB19: =IF(OR(K19="",G19=""),"",S19*Settings!$B$13) | AC19: =IF(OR(K19="",G19=""),"",Z19-AA19-AB19-J19) | AD19: =IF(OR(K19="",G19=""),"",AC19*Settings!$B$14) | AE19: =IF(OR(K19="",G19=""),"",IF(S19=0,"",AC19/S19)) | AF19: =IF(OR(K19="",G19=""),"",IF(J19=0,"",AC19/J19)) | AG19: =IF(OR(K19="",G19=""),"",(J19+V19)/(1-(1+Settings!$B$10)*(IF(N19="",Settings!$B$5,N19)+IF(M19="",Settings!$B$11,M19))-IF(UPPER(O19)="Y",Settings!$B$9,0)-Settings!$B$13-Settings!$B$12)-N(L19)) | AH19: =IF(OR(K19="",G19=""),"",(J19+V19+Settings!$B$15)/(1-(1+Settings!$B$10)*(IF(N19="",Settings!$B$5,N19)+IF(M19="",Settings!$B$11,M19))-IF(UPPER(O19)="Y",Settings!$B$9,0)-Settings!$B$13-Settings!$B$12)-N(L19)) | AI19: =IF(C19="","",IF(OR(ISNUMBER(SEARCH("amazon",C19)),ISNUMBER(SEARCH("walmart",C19)),ISNUMBER(SEARCH("aliexpress",C19)),ISNUMBER(SEARCH("temu",C19))),"⚠ Retail source — not allowed","✓ Wholesale / own stock")) | AJ19: =IF(OR(K19="",G19=""),"",IF(LEFT(AI19,1)="⚠","❌ SKIP",IF(AND(AC19>=Settings!$B$15,AF19>=Settings!$B$16,OR(R19="",N(R19)>=Settings!$B$17)),"✅ GO",IF(AC19>0,"⚠ CHECK","❌ SKIP"))))
... A204: =IF(B204="","",ROW()-4) | J204: =IF(G204="","",G204+N(H204)+N(I204)) | R204: =IF(OR(P204="",Q204=""),"",P204/(P204+Q204)) | S204: =IF(OR(K204="",G204=""),"",K204+N(L204)) | T204: =IF(OR(K204="",G204=""),"",S204*Settings!$B$10) | U204: =IF(OR(K204="",G204=""),"",(S204+T204)*IF(N204="",Settings!$B$5,N204)) | V204: =IF(OR(K204="",G204=""),"",IF(S204+T204<=Settings!$B$8,Settings!$B$6,Settings!$B$7)) | W204: =IF(OR(K204="",G204=""),"",S204*IF(UPPER(O204)="Y",Settings!$B$9,0)) | X204: =IF(OR(K204="",G204=""),"",(S204+T204)*IF(M204="",Settings!$B$11,M204)) | Y204: =IF(OR(K204="",G204=""),"",U204+V204+W204+X204) | Z204: =IF(OR(K204="",G204=""),"",S204-Y204) | AA204: =IF(OR(K204="",G204=""),"",Z204*Settings!$B$12) | AB204: =IF(OR(K204="",G204=""),"",S204*Settings!$B$13) | AC204: =IF(OR(K204="",G204=""),"",Z204-AA204-AB204-J204) | AD204: =IF(OR(K204="",G204=""),"",AC204*Settings!$B$14) | AE204: =IF(OR(K204="",G204=""),"",IF(S204=0,"",AC204/S204)) | AF204: =IF(OR(K204="",G204=""),"",IF(J204=0,"",AC204/J204)) | AG204: =IF(OR(K204="",G204=""),"",(J204+V204)/(1-(1+Settings!$B$10)*(IF(N204="",Settings!$B$5,N204)+IF(M204="",Settings!$B$11,M204))-IF(UPPER(O204)="Y",Settings!$B$9,0)-Settings!$B$13-Settings!$B$12)-N(L204)) | AH204: =IF(OR(K204="",G204=""),"",(J204+V204+Settings!$B$15)/(1-(1+Settings!$B$10)*(IF(N204="",Settings!$B$5,N204)+IF(M204="",Settings!$B$11,M204))-IF(UPPER(O204)="Y",Settings!$B$9,0)-Settings!$B$13-Settings!$B$12)-N(L204)) | AI204: =IF(C204="","",IF(OR(ISNUMBER(SEARCH("amazon",C204)),ISNUMBER(SEARCH("walmart",C204)),ISNUMBER(SEARCH("aliexpress",C204)),ISNUMBER(SEARCH("temu",C204))),"⚠ Retail source — not allowed","✓ Wholesale / own stock")) | AJ204: =IF(OR(K204="",G204=""),"",IF(LEFT(AI204,1)="⚠","❌ SKIP",IF(AND(AC204>=Settings!$B$15,AF204>=Settings!$B$16,OR(R204="",N(R204)>=Settings!$B$17)),"✅ GO",IF(AC204>0,"⚠ CHECK","❌ SKIP"))))

Sheet Read Me
B2: How to use
B3: 1. Hunting tab: add one product per row. Fill only the YELLOW columns (blue text).
B4: 2. Grey columns calculate fees, profit, ROI, break-even price and a GO / CHECK / SKIP status.
B5: 3. Settings tab: change fee rates, tax, ad rate, PKR rate and your GO rules in one place.
B6: 4. Dashboard tab: totals and the top 5 products by profit. Delete the 3 example rows when you start.
B8: What the status means
B9: ✅ GO — profit ≥ minimum, ROI ≥ minimum, sell-through ≥ minimum (if you entered sold/active), and the source is allowed.
B10: ⚠ CHECK — profitable, but below one of your rules. Look again at price, cost or demand.
B11: ❌ SKIP — loss, or the source is a retail site that eBay does not allow for drop shipping.
B13: eBay rules to remember (2026)
B14: • Drop shipping is only allowed from WHOLESALE suppliers. Buying from Amazon, Walmart, AliExpress or Temu and shipping to the buyer is not allowed.
B15: • A Pakistan-registered account cannot list items located outside Pakistan without eBay approval (error e301005). Item location must be true.
... B20: frooition.com/ebay-fee-calculator · sellerfeecalc.com/ebay-fees/final-value-fee · flowlister.com/blog/ebay-final-value-fees-explained
